{
    "groups": [
        {
            "title": "Getting-Started",
            "pages": [
                {
                    "title": "Quickstart",
                    "source": "../documentation/quickstart.md"
                },
                {
                    "title": "Config.js Reference",
                    "source": "../documentation/config-reference.md"
                },
                {
                    "title": "Writing tests",
                    "source": "../documentation/writing-tests.md"
                },
                {
                    "title": "Tips and Reference",
                    "source": "../documentation/reference-tips.md"
                },
                {
                    "title": "Links, and more links",
                    "source": "../documentation/learn-more.md"
                }
            ]
        }
    ],
    "output": "pages",
    "listInvalidSymbolLinks": false,
    "reflectionNavigationTitle": "Helper Methods"
}
